jvav/__init__.py
jvav/cmd.py
jvav/utils.py
jvav-3.0.0.dist-info/licenses/LICENSE
jvav-3.0.0.dist-info/METADATA
jvav-3.0.0.dist-info/WHEEL
jvav-3.0.0.dist-info/entry_points.txt
jvav-3.0.0.dist-info/top_level.txt
jvav-3.0.0.dist-info/RECORD
