Metadata-Version: 2.4
Name: Jvav
Version: 3.0.0
Summary: [NSFW] Useful tools for crawling study resources.
Home-page: https://github.com/akynazh/jvav
Download-URL: https://github.com/akynazh/jvav/releases/latest
Author: akynazh
Author-email: akynazh@gmail.com
License: GPLv3
Project-URL: Tracker, https://github.com/akynazh/jvav/issues
Project-URL: Source, https://github.com/akynazh/jvav
Keywords: nsfw japan video api library python spider jav adult
Classifier: License :: OSI Approved :: GNU General Public License v3 (GPLv3)
Classifier: Operating System :: OS Independent
Classifier: Programming Language :: Python :: 3
Classifier: Topic :: Internet :: WWW/HTTP :: Indexing/Search
Requires-Python: ~=3.9
License-File: LICENSE
Requires-Dist: anti-useragent>=1.0.10
Requires-Dist: attrs>=23.2.0
Requires-Dist: beautifulsoup4>=4.11.2
Requires-Dist: build>=1.0.3
Requires-Dist: cattrs>=23.1.2
Requires-Dist: certifi>=2023.11.17
Requires-Dist: charset-normalizer>=3.3.2
Requires-Dist: click>=8.1.7
Requires-Dist: deep-translator>=1.11.4
Requires-Dist: exceptiongroup>=1.2.0
Requires-Dist: idna>=3.6
Requires-Dist: importlib-metadata>=6.7.0
Requires-Dist: langdetect>=1.0.9
Requires-Dist: loguru>=0.7.2
Requires-Dist: lxml>=4.9.2
Requires-Dist: mypy-extensions>=1.0.0
Requires-Dist: packaging>=23.2
Requires-Dist: pathspec>=0.11.2
Requires-Dist: platformdirs>=4.0.0
Requires-Dist: pyproject-hooks>=1.0.0
Requires-Dist: requests>=2.31.0
Requires-Dist: requests-cache>=1.1.1
Requires-Dist: six>=1.16.0
Requires-Dist: soupsieve>=2.4.1
Requires-Dist: tomli>=2.0.1
Requires-Dist: typed-ast>=1.5.5
Requires-Dist: typing-extensions>=4.7.1
Requires-Dist: url-normalize>=1.4.3
Requires-Dist: urllib3>=2.0.7
Requires-Dist: Wikipedia-API>=0.5.8
Requires-Dist: zipp>=3.15.0
Requires-Dist: pytest
Requires-Dist: twine
Dynamic: author
Dynamic: author-email
Dynamic: classifier
Dynamic: description
Dynamic: description-content-type
Dynamic: download-url
Dynamic: home-page
Dynamic: keywords
Dynamic: license
Dynamic: license-file
Dynamic: project-url
Dynamic: requires-dist
Dynamic: requires-python
Dynamic: summary
